arpa_backport/__init__.py
arpa_backport/api.py
arpa_backport/exceptions.py
arpa_backport/models/__init__.py
arpa_backport/models/base.py
arpa_backport/models/simple.py
arpa_backport/parsers/__init__.py
arpa_backport/parsers/base.py
arpa_backport/parsers/quick.py
arpa_backport-0.1.0b4.dist-info/AUTHORS.md
arpa_backport-0.1.0b4.dist-info/LICENSE
arpa_backport-0.1.0b4.dist-info/METADATA
arpa_backport-0.1.0b4.dist-info/WHEEL
arpa_backport-0.1.0b4.dist-info/top_level.txt
arpa_backport-0.1.0b4.dist-info/zip-safe
arpa_backport-0.1.0b4.dist-info/RECORD
