Metadata-Version: 2.1
Name: arpa-backport
Version: 0.1.0b4
Summary: Library for reading ARPA n-gram models with Python 2.7.
Home-page: https://github.com/sfischer13/python-arpa
Author: Stefan Fischer
Author-email: sfischer13@ymail.com
License: MIT
Project-URL: bug tracker, https://github.com/sfischer13/python-arpa/issues/
Project-URL: documentation, https://arpa.readthedocs.io/
Project-URL: source code, https://github.com/sfischer13/python-arpa/
Keywords: A,R,P,A, ,n,-,g,r,a,m, ,n,g,r,a,m, ,l,a,n,g,u,a,g,e, ,m,o,d,e,l, ,L,M, ,l,a,n,g,u,a,g,e, ,t,e,c,h,n,o,l,o,g,y, ,L,T, ,c,o,m,p,u,t,a,t,i,o,n,a,l, ,l,i,n,g,u,i,s,t,i,c,s, ,C,L, ,n,a,t,u,r,a,l, ,l,a,n,g,u,a,g,e, ,p,r,o,c,e,s,s,i,n,g, ,N,L,P, ,u,n,i,g,r,a,m, ,b,i,g,r,a,m, ,t,r,i,g,r,a,m
Platform: UNKNOWN
Classifier: Development Status :: 4 - Beta
Classifier: Intended Audience :: Developers
Classifier: Intended Audience :: Information Technology
Classifier: Intended Audience :: Science/Research
Classifier: License :: OSI Approved :: MIT License
Classifier: Operating System :: OS Independent
Classifier: Programming Language :: Python
Classifier: Programming Language :: Python :: 2
Classifier: Programming Language :: Python :: 2.7
Classifier: Programming Language :: Python :: 2 :: Only
Classifier: Programming Language :: Python :: Implementation
Classifier: Programming Language :: Python :: Implementation :: CPython
Classifier: Topic :: Scientific/Engineering
Classifier: Topic :: Scientific/Engineering :: Artificial Intelligence
Classifier: Topic :: Software Development :: Libraries
Classifier: Topic :: Software Development :: Libraries :: Python Modules
Classifier: Topic :: Text Processing
Classifier: Topic :: Text Processing :: Linguistic
Requires-Python: ~=2.7
Requires-Dist: enum34
